tidydata/__init__.py
tidydata/base.py
tidydata/dtype.py
tidydata/io.py
tidydata/pandas_extension.py
tidydata/polars_extension.py
tidydata/schema.py
tidydata/table.py
tidydata/tidydata.py
tidydata/utils.py
tidydata-0.1.19.dist-info/METADATA
tidydata-0.1.19.dist-info/WHEEL
tidydata-0.1.19.dist-info/RECORD
