Metadata-Version: 2.1
Name: tidydata
Version: 0.1.19
Summary: Data Cleaner for multiple files
Author: kyrie1218
Author-email: kyrie1218@163.com
Requires-Python: >=3.11,<4.0
Classifier: Programming Language :: Python :: 3
Classifier: Programming Language :: Python :: 3.11
Classifier: Programming Language :: Python :: 3.12
Requires-Dist: click (==8.1.7)
Requires-Dist: diskcache (==5.6.3)
Requires-Dist: emoji (==2.9.0)
Requires-Dist: ipykernel (==6.27.1)
Requires-Dist: loguru (==0.7.2)
Requires-Dist: pandas[compression,excel,feather,hdf5,html,output-formatting,parquet,performance,spss] (==2.1.4)
Requires-Dist: polars (==0.19.19)
Requires-Dist: py-ulid (==1.0.3)
Requires-Dist: pydantic (==2.5.2)
Requires-Dist: pyyaml (==6.0.1)
Requires-Dist: rich (==13.7.0)
Requires-Dist: seedir (==0.4.2)
Requires-Dist: stata-setup (==0.1.3)
Requires-Dist: toml (==0.10.2)
Requires-Dist: typeguard (==4.1.5)
